cloudsculpter/__init__.py
cloudsculpter/create.py
cloudsculpter/deploy.py
cloudsculpter/edit.py
cloudsculpter/fix.py
cloudsculpter/logger.py
cloudsculpter/main.py
cloudsculpter/utils.py
cloudsculpter-0.0.2.dist-info/METADATA
cloudsculpter-0.0.2.dist-info/WHEEL
cloudsculpter-0.0.2.dist-info/entry_points.txt
cloudsculpter-0.0.2.dist-info/top_level.txt
cloudsculpter-0.0.2.dist-info/RECORD
