Metadata-Version: 2.1
Name: cloudsculpter
Version: 0.0.2
Summary: A package to deploy cloudformation resources with natural language instructions, automatically healing failed deployments with OpenAI troubleshooting
Home-page: https://github.com/righteousgambit/cloudsculpter
Author: Wes Ladd
Author-email: wesladd@traingrc.com
Classifier: Programming Language :: Python :: 3
Classifier: License :: OSI Approved :: MIT License
Classifier: Operating System :: OS Independent
Requires-Python: >=3.6
Requires-Dist: boto3
Requires-Dist: openai
Requires-Dist: pyyaml
Requires-Dist: termcolor
